viscube/__init__.py
viscube/__meta__.py
viscube/grid_cube.py
viscube/gridder.py
viscube/windows.py
viscube-0.0.1.dist-info/licenses/LICENSE
viscube-0.0.1.dist-info/METADATA
viscube-0.0.1.dist-info/WHEEL
viscube-0.0.1.dist-info/top_level.txt
viscube-0.0.1.dist-info/RECORD
